{"chunk_definitions":[{"row":27,"row_count":1,"visible":true,"expansion_state":0,"options":{"engine":"r","label":"packages","message":false,"dev":"png"},"document_id":"C4144292","chunk_id":"cfkh07kknafvt","chunk_label":"packages"},{"row":39,"row_count":1,"visible":true,"expansion_state":0,"options":{"engine":"r","label":"faux_nodes","echo":false,"dev":"png"},"document_id":"C4144292","chunk_id":"c9tnax3o0tg5s","chunk_label":"faux_nodes"},{"row":48,"row_count":1,"visible":true,"expansion_state":0,"options":{"engine":"r","label":"triad_mat","dev":"png"},"document_id":"C4144292","chunk_id":"cc7xq73zsex97","chunk_label":"triad_mat"},{"row":81,"row_count":1,"visible":true,"expansion_state":0,"options":{"engine":"r","label":"ngq_egos","dev":"png"},"document_id":"C4144292","chunk_id":"cjlb66a1v3a1j","chunk_label":"ngq_egos"},{"row":87,"row_count":1,"visible":true,"expansion_state":0,"options":{"engine":"r","label":"ngq_alters","dev":"png"},"document_id":"C4144292","chunk_id":"cfi389ircoewr","chunk_label":"ngq_alters"},{"row":93,"row_count":1,"visible":true,"expansion_state":0,"options":{"engine":"r","label":"ngq_aa","dev":"png"},"document_id":"C4144292","chunk_id":"cqug2x4jvzyrf","chunk_label":"ngq_aa"},{"row":137,"row_count":1,"visible":true,"expansion_state":0,"options":{"engine":"r","label":"igraph_setup","dev":"png"},"document_id":"C4144292","chunk_id":"c7xqj0j0vxvkn","chunk_label":"igraph_setup"},{"row":152,"row_count":1,"visible":true,"expansion_state":0,"options":{"engine":"r","label":"indegree","dev":"png"},"document_id":"C4144292","chunk_id":"c5hckm8vgjypg","chunk_label":"indegree"},{"row":160,"row_count":1,"visible":true,"expansion_state":0,"options":{"engine":"r","label":"outdegree","dev":"png"},"document_id":"C4144292","chunk_id":"c33hxz9zjele6","chunk_label":"outdegree"},{"row":168,"row_count":1,"visible":true,"expansion_state":0,"options":{"engine":"r","label":"total_degree","dev":"png"},"document_id":"C4144292","chunk_id":"cnob3c37fahej","chunk_label":"total_degree"},{"row":177,"row_count":1,"visible":true,"expansion_state":0,"options":{"engine":"r","label":"betweenness","dev":"png"},"document_id":"C4144292","chunk_id":"coev3mrz84tzo","chunk_label":"betweenness"},{"row":187,"row_count":1,"visible":true,"expansion_state":0,"options":{"engine":"r","label":"closeness","dev":"png"},"document_id":"C4144292","chunk_id":"c4tsc91hovzs0","chunk_label":"closeness"},{"row":199,"row_count":1,"visible":true,"expansion_state":0,"options":{"engine":"r","label":"eigen","dev":"png"},"document_id":"C4144292","chunk_id":"czmn7ccss99r5","chunk_label":"eigen"},{"row":212,"row_count":1,"visible":true,"expansion_state":0,"options":{"engine":"r","label":"cent_df","dev":"png"},"document_id":"C4144292","chunk_id":"c3rej6it18zjk","chunk_label":"cent_df"},{"row":223,"row_count":1,"visible":true,"expansion_state":0,"options":{"engine":"r","label":"density","dev":"png"},"document_id":"C4144292","chunk_id":"c1hp86h684ika","chunk_label":"density"},{"row":232,"row_count":1,"visible":true,"expansion_state":0,"options":{"engine":"r","label":"clustering","dev":"png"},"document_id":"C4144292","chunk_id":"cp4oxh1lzccbx","chunk_label":"clustering"},{"row":249,"row_count":1,"visible":true,"expansion_state":0,"options":{"engine":"r","label":"igraph_plot","dev":"png"},"document_id":"C4144292","chunk_id":"cvkril2ghw8tb","chunk_label":"igraph_plot"},{"row":291,"row_count":1,"visible":true,"expansion_state":0,"options":{"engine":"r","label":"nw_faux","warning":false,"dev":"png"},"document_id":"C4144292","chunk_id":"cftbpf9t5zvuf","chunk_label":"nw_faux"},{"row":297,"row_count":1,"visible":true,"expansion_state":0,"options":{"engine":"r","label":"list2env","dev":"png"},"document_id":"C4144292","chunk_id":"cghe5n6d28nbq","chunk_label":"list2env"},{"row":305,"row_count":1,"visible":true,"expansion_state":0,"options":{"engine":"r","label":"system_measure_plot","fig.height":4,"fig.width":7,"dev":"png"},"document_id":"C4144292","chunk_id":"cii2g9m2pcfaw","chunk_label":"system_measure_plot"},{"row":311,"row_count":1,"visible":true,"expansion_state":0,"options":{"engine":"r","label":"system_level_measures","dev":"png"},"document_id":"C4144292","chunk_id":"c06sx20qylev6","chunk_label":"system_level_measures"},{"row":317,"row_count":1,"visible":true,"expansion_state":0,"options":{"engine":"r","label":"igraph_object","dev":"png"},"document_id":"C4144292","chunk_id":"c4o6u7bhm1q9q","chunk_label":"igraph_object"},{"row":323,"row_count":1,"visible":true,"expansion_state":0,"options":{"engine":"r","label":"edgelist","dev":"png"},"document_id":"C4144292","chunk_id":"c18dfipf37unu","chunk_label":"edgelist"},{"row":329,"row_count":1,"visible":true,"expansion_state":0,"options":{"engine":"r","label":"node_measures","dev":"png"},"document_id":"C4144292","chunk_id":"c8opv45xzzm97","chunk_label":"node_measures"},{"row":335,"row_count":1,"visible":true,"expansion_state":0,"options":{"engine":"r","label":"node_measure_plot","fig.height":6,"fig.width":7,"dev":"png"},"document_id":"C4144292","chunk_id":"cptck9f6ge9zk","chunk_label":"node_measure_plot"},{"row":348,"row_count":1,"visible":true,"expansion_state":0,"options":{"engine":"r","label":"nw_triad","warning":false,"dev":"png"},"document_id":"C4144292","chunk_id":"c9wo0qqc7cq3u","chunk_label":"nw_triad"},{"row":358,"row_count":1,"visible":true,"expansion_state":0,"options":{"engine":"r","label":"florentine_head","dev":"png"},"document_id":"C4144292","chunk_id":"cubrv9wvdyib9","chunk_label":"florentine_head"},{"row":372,"row_count":1,"visible":true,"expansion_state":0,"options":{"engine":"r","label":"nw_flor","warning":false,"dev":"png"},"document_id":"C4144292","chunk_id":"cu3jz5ewy67oc","chunk_label":"nw_flor"},{"row":378,"row_count":1,"visible":true,"expansion_state":0,"options":{"engine":"r","label":"edgelist_business","dev":"png"},"document_id":"C4144292","chunk_id":"cauh194jaq7mv","chunk_label":"edgelist_business"},{"row":382,"row_count":1,"visible":true,"expansion_state":0,"options":{"engine":"r","label":"edgelist_summary","dev":"png"},"document_id":"C4144292","chunk_id":"cnh74wcynupc8","chunk_label":"edgelist_summary"},{"row":390,"row_count":1,"visible":true,"expansion_state":0,"options":{"engine":"r","label":"total_degree_type","dev":"png"},"document_id":"C4144292","chunk_id":"cogt6mkblcrse","chunk_label":"total_degree_type"},{"row":396,"row_count":1,"visible":true,"expansion_state":0,"options":{"engine":"r","label":"system_measures_multi","dev":"png"},"document_id":"C4144292","chunk_id":"co60oaotu3ckf","chunk_label":"system_measures_multi"},{"row":408,"row_count":1,"visible":true,"expansion_state":0,"options":{"engine":"r","label":"flor_igraph","fig.height":4,"fig.width":7,"dev":"png"},"document_id":"C4144292","chunk_id":"ci1whb5rhaj5g","chunk_label":"flor_igraph"},{"row":416,"row_count":1,"visible":true,"expansion_state":0,"options":{"engine":"r","eval":false,"label":"unnamed-chunk-1","dev":"png"},"document_id":"C4144292","chunk_id":"cixkmkyhasx1d","chunk_label":"unnamed-chunk-1"}],"doc_write_time":1713812889,"chunk_rendered_width":700}